django_google_maps_widget/__init__.py
django_google_maps_widget/fields.py
django_google_maps_widget/models.py
django_google_maps_widget/widgets.py
django_google_maps_widget/static/django_google_maps_widget/css/google-maps-admin.css
django_google_maps_widget/static/django_google_maps_widget/js/google-maps-admin.js
django_google_maps_widget/templates/django_google_maps_widget/widgets/map_widget.html
django_google_maps_widget/tests/__init__.py
django_google_maps_widget/tests/test_geolocation_field.py
django_google_maps_widget/tests/test_geopt_field.py
django_google_maps_widget/tests/test_typename.py
django_google_maps_widget/tests/test_widget.py
django_google_maps_widget/tests/test_app/__init__.py
django_google_maps_widget/tests/test_app/models.py
django_google_maps_widget-1.0.0.dist-info/METADATA
django_google_maps_widget-1.0.0.dist-info/WHEEL
django_google_maps_widget-1.0.0.dist-info/licenses/LICENSE
django_google_maps_widget-1.0.0.dist-info/RECORD
