Metadata-Version: 2.3
Name: django-google-maps-widget
Version: 1.0.0
Summary: Plugs Google Maps Platform API into Django admin.
Project-URL: Homepage, https://github.com/amv-bamboo/django-google-maps-widget
Project-URL: Issues, https://github.com/amv-bamboo/django-google-maps-widget/issues
Author-email: Aaron Madison <aaron.l.madison@gmail.com>, Andrei Mukamolau <amv@bamboogroup.eu>
Maintainer-email: Andrei Mukamolau <amv@bamboogroup.eu>
License: Copyright (c) 2011, Aaron Madison
Classifier: Development Status :: 5 - Production/Stable
Classifier: Environment :: Web Environment
Classifier: Framework :: Django
Classifier: Framework :: Django :: 4.2
Classifier: Framework :: Django :: 5.0
Classifier: Framework :: Django :: 5.1
Classifier: Intended Audience :: Developers
Classifier: License :: OSI Approved :: BSD License
Classifier: Operating System :: OS Independent
Classifier: Programming Language :: Python
Classifier: Programming Language :: Python :: 3.9
Classifier: Programming Language :: Python :: 3.10
Classifier: Programming Language :: Python :: 3.11
Classifier: Programming Language :: Python :: 3.12
Classifier: Programming Language :: Python :: 3.13
Classifier: Topic :: Software Development
Classifier: Topic :: Software Development :: Libraries :: Application Frameworks
Requires-Python: >=3.9
Requires-Dist: django>=4.2
